[
  {
    "Id": 1,
    "company": "TechCorp Inc",
    "contactPerson": "Sarah Johnson",
    "email": "sarah.johnson@techcorp.com",
    "phone": "+1 (555) 123-4567",
    "industry": "Technology",
    "lastContactDate": "2023-12-10",
    "notes": "Interested in our premium package. Discussed implementation timeline and pricing. Next meeting scheduled for Q1 2024.",
    "createdAt": "2023-10-15T09:30:00.000Z",
    "updatedAt": "2023-12-10T14:20:00.000Z"
  },
  {
    "Id": 2,
    "company": "Innovation Labs",
    "contactPerson": "Mike Chen",
    "email": "mike.chen@innovationlabs.com",
    "phone": "+1 (555) 234-5678",
    "industry": "Healthcare",
    "lastContactDate": "2023-12-08",
    "notes": "Decision maker for healthcare solutions. Requested detailed proposal for their new facility expansion.",
    "createdAt": "2023-09-22T11:15:00.000Z",
    "updatedAt": "2023-12-08T10:45:00.000Z"
  },
  {
    "Id": 3,
    "company": "Global Solutions",
    "contactPerson": "Alice Brown",
    "email": "alice.brown@globalsolutions.com",
    "phone": "+1 (555) 345-6789",
    "industry": "Finance",
    "lastContactDate": "2023-12-07",
    "notes": "CFO at Global Solutions. Very interested in cost-saving opportunities. Scheduled follow-up for January.",
    "createdAt": "2023-11-03T16:45:00.000Z",
    "updatedAt": "2023-12-07T09:30:00.000Z"
  },
  {
    "Id": 4,
    "company": "StartupXYZ",
    "contactPerson": "David Wilson",
    "email": "david@startupxyz.com",
    "phone": "+1 (555) 456-7890",
    "industry": "Technology",
    "lastContactDate": "2023-12-06",
    "notes": "Early-stage startup looking for scalable solutions. Budget constraints but high growth potential.",
    "createdAt": "2023-11-20T13:20:00.000Z",
    "updatedAt": "2023-12-06T15:10:00.000Z"
  },
  {
    "Id": 5,
    "company": "Education First",
    "contactPerson": "Jennifer Lee",
    "email": "jennifer.lee@educationfirst.org",
    "phone": "+1 (555) 567-8901",
    "industry": "Education",
    "lastContactDate": "2023-12-05",
    "notes": "Non-profit organization. Interested in educational discounts. Needs board approval for any purchases.",
    "createdAt": "2023-10-28T08:00:00.000Z",
    "updatedAt": "2023-12-05T12:30:00.000Z"
  },
  {
    "Id": 6,
    "company": "Manufacturing Pro",
    "contactPerson": "Robert Martinez",
    "email": "robert.martinez@mfgpro.com",
    "phone": "+1 (555) 678-9012",
    "industry": "Manufacturing",
    "lastContactDate": "2023-12-04",
    "notes": "Plant manager interested in efficiency improvements. Requested on-site demonstration for March 2024.",
    "createdAt": "2023-09-15T14:30:00.000Z",
    "updatedAt": "2023-12-04T11:00:00.000Z"
  },
  {
    "Id": 7,
    "company": "Retail Giants",
    "contactPerson": "Lisa Thompson",
    "email": "lisa.thompson@retailgiants.com",
    "phone": "+1 (555) 789-0123",
    "industry": "Retail",
    "lastContactDate": "2023-12-03",
    "notes": "VP of Operations. Looking to modernize their inventory management system. High-priority prospect.",
    "createdAt": "2023-11-10T10:15:00.000Z",
    "updatedAt": "2023-12-03T16:20:00.000Z"
  },
  {
    "Id": 8,
    "company": "Real Estate Plus",
    "contactPerson": "Kevin O'Connor",
    "email": "kevin@realestateplus.com",
    "phone": "+1 (555) 890-1234",
    "industry": "Real Estate",
    "lastContactDate": "2023-12-02",
    "notes": "Broker looking for client management solutions. Interested in mobile capabilities for field agents.",
    "createdAt": "2023-10-05T12:45:00.000Z",
    "updatedAt": "2023-12-02T09:15:00.000Z"
  },
  {
    "Id": 9,
    "company": "Consulting Partners",
    "contactPerson": "Emma Rodriguez",
    "email": "emma.rodriguez@consultingpartners.com",
    "phone": "+1 (555) 901-2345",
    "industry": "Consulting",
    "lastContactDate": "2023-12-01",
    "notes": "Senior partner evaluating tools for client project management. Requires integration with existing systems.",
    "createdAt": "2023-11-18T15:30:00.000Z",
    "updatedAt": "2023-12-01T13:45:00.000Z"
  },
  {
    "Id": 10,
    "company": "Media House",
    "contactPerson": "James Foster",
    "email": "james.foster@mediahouse.com",
    "phone": "+1 (555) 012-3456",
    "industry": "Media",
    "lastContactDate": "2023-11-30",
    "notes": "Creative director interested in project collaboration tools. Budget approved for Q1 implementation.",
    "createdAt": "2023-09-30T11:00:00.000Z",
    "updatedAt": "2023-11-30T14:30:00.000Z"
  },
  {
    "Id": 11,
    "company": "Government Solutions",
    "contactPerson": "Patricia Adams",
    "email": "patricia.adams@govsolutions.gov",
    "phone": "+1 (555) 123-4568",
    "industry": "Government",
    "lastContactDate": "2023-11-29",
    "notes": "Program manager for digital transformation initiative. Requires compliance with government standards.",
    "createdAt": "2023-08-15T09:20:00.000Z",
    "updatedAt": "2023-11-29T10:30:00.000Z"
  },
  {
    "Id": 12,
    "company": "Charity Works",
    "contactPerson": "Thomas Green",
    "email": "thomas.green@charityworks.org",
    "phone": "+1 (555) 234-5679",
    "industry": "Non-Profit",
    "lastContactDate": "2023-11-28",
    "notes": "Executive director seeking donor management solutions. Limited budget but passionate about the mission.",
    "createdAt": "2023-10-12T16:10:00.000Z",
    "updatedAt": "2023-11-28T12:00:00.000Z"
  }
]